[
  {
    "title": "Boeing aims to certify 737 MAX variants by year-end, CEO tells Aviation Week",
    "link": "https://finance.yahoo.com/news/boeing-aims-certify-737-max-003920836.html"
  },
  {
    "title": "3 Reasons Boeing Stock Is a Buy",
    "link": "https://finance.yahoo.com/news/3-reasons-boeing-stock-buy-223200129.html"
  },
  {
    "title": "Astronics vs. Ducommun: Which Aerospace Supplier Is the Better Player Now?",
    "link": "https://finance.yahoo.com/news/astronics-vs-ducommun-aerospace-supplier-150800625.html"
  },
  {
    "title": "Investors Heavily Search The Boeing Company (BA): Here is What You Need to Know",
    "link": "https://finance.yahoo.com/news/investors-heavily-search-boeing-company-130015229.html"
  },
  {
    "title": "Boeing, DOJ reach $1.1B deal to drop plane crash criminal charges",
    "link": "https://finance.yahoo.com/news/boeing-doj-reach-1-1b-113755158.html"
  },
  {
    "title": "Qatar Airways CEO & Ex Virgin Australia CEO on Aviation Industry",
    "link": "https://finance.yahoo.com/video/qatar-airways-ceo-ex-virgin-103901043.html"
  },
  {
    "title": "Exclusive-Aircraft leasing giant calls on Trump to expand zero-tariff plane pact",
    "link": "https://finance.yahoo.com/news/exclusive-aircraft-leasing-giant-calls-090317728.html"
  },
  {
    "title": "1 Unpopular Stock that Deserves a Second Chance and 2 to Be Wary Of",
    "link": "https://finance.yahoo.com/news/1-unpopular-stock-deserves-second-043233080.html"
  },
  {
    "title": "Jim Cramer Calls The Boeing Company (BA) “an Up Stock”",
    "link": "https://finance.yahoo.com/news/jim-cramer-calls-boeing-company-215522348.html"
  },
  {
    "title": "Boeing Stock Slips Despite Deal With Trump’s Justice Department",
    "link": "https://finance.yahoo.com/m/bd2d4202-9a30-3427-b797-802ae08ca939/boeing-stock-slips-despite.html"
  },
  {
    "title": "CMA CGM’s $600M Vietnam Port Project Reflects ‘Sharp’ Container Demand",
    "link": "https://finance.yahoo.com/news/cma-cgm-600m-vietnam-port-201500336.html"
  },
  {
    "title": "These Stocks Moved the Most Today: Apple, Tesla, DJT, Informatica, Super Micro, PDD, SoundHound, and More",
    "link": "https://finance.yahoo.com/m/cb115b68-1a25-3db8-b902-2423a35b8aca/these-stocks-moved-the-most.html"
  },
  {
    "title": "Why Shares in Airbus Took Off Today",
    "link": "https://finance.yahoo.com/news/why-shares-airbus-took-off-182720025.html"
  },
  {
    "title": "April Durable Goods Orders Drop Less Than Feared as Transportation Equipment Weighs",
    "link": "https://finance.yahoo.com/news/april-durable-goods-orders-drop-174212243.html"
  },
  {
    "title": "Ryanair's EPS Estimates Northbound: Time to Buy the Stock?",
    "link": "https://finance.yahoo.com/news/ryanairs-eps-estimates-northbound-time-160600807.html"
  },
  {
    "title": "US and EU Race for Trade Deal With Six Weeks Left Until Truce Expires",
    "link": "https://finance.yahoo.com/news/eu-focus-critical-sectors-bid-081132717.html"
  },
  {
    "title": "Lockheed Wins a $214M Contract to Aid Multiple Launch Rocket System",
    "link": "https://finance.yahoo.com/news/lockheed-wins-214m-contract-aid-143100740.html"
  },
  {
    "title": "EU Plans to ‘Fast Track’ Trade Talks With US Amid Tariff Fight",
    "link": "https://finance.yahoo.com/news/eu-plans-fast-track-trade-142009568.html"
  },
  {
    "title": "UAL vs. CPA: Which Airline Stock is a Stronger Play Now?",
    "link": "https://finance.yahoo.com/news/ual-vs-cpa-airline-stock-134100045.html"
  },
  {
    "title": "Germany’s Merz Says US Tech Perks Could Be Target in Trade War",
    "link": "https://finance.yahoo.com/news/germany-merz-says-us-tech-122020592.html"
  },
  {
    "title": "EasyJet pounces on Ryanair woes as budget rivalry reignites",
    "link": "https://finance.yahoo.com/news/easyjet-pounces-ryanair-woes-budget-110000833.html"
  },
  {
    "title": "Boeing in Tentative Agreement to Pay $1.1 Billion to Avoid Trial for 737 MAX Crashes",
    "link": "https://finance.yahoo.com/m/a7053ebc-ab96-31db-b6c9-dca8781f719b/boeing-in-tentative-agreement.html"
  },
  {
    "title": "Boeing vs. Airbus: Which Aviation Titan Offers Better Long-Term Prospects?",
    "link": "https://finance.yahoo.com/news/boeing-vs-airbus-aviation-titan-200800083.html"
  },
  {
    "title": "Boeing's $444M Escape Plan? DOJ Deal Could Kill Trial Over Deadly Crashes",
    "link": "https://finance.yahoo.com/news/boeings-444m-escape-plan-doj-195122342.html"
  },
  {
    "title": "Boeing reaches deal with DOJ, avoids 737 Max prosecution",
    "link": "https://finance.yahoo.com/video/boeing-reaches-deal-doj-avoids-193856762.html"
  },
  {
    "title": "Justice Department reaches deal to allow Boeing to avoid prosecution over 737 Max crashes",
    "link": "https://finance.yahoo.com/news/justice-department-reaches-deal-allow-185921076.html"
  },
  {
    "title": "Justice Department and Boeing reach deal allowing airplane giant to avoid prosecution over 737 Max crashes",
    "link": "https://finance.yahoo.com/news/justice-department-boeing-reach-deal-185408375.html"
  },
  {
    "title": "US Justice Department reaches deal with Boeing to allow planemaker to avoid prosecution",
    "link": "https://finance.yahoo.com/news/us-justice-department-reaches-deal-183318286.html"
  },
  {
    "title": "European Officials Urge ‘Calm’ Facing Trump 50% Tariff Threat",
    "link": "https://finance.yahoo.com/news/european-officials-urge-calm-facing-155838237.html"
  },
  {
    "title": "Boeing (BA) Up 15.4% Since Last Earnings Report: Can It Continue?",
    "link": "https://finance.yahoo.com/news/boeing-ba-15-4-since-153049465.html"
  },
  {
    "title": "US senators urge DOJ not to let Boeing avoid criminal prosecution",
    "link": "https://finance.yahoo.com/news/us-senators-urge-doj-not-150907656.html"
  },
  {
    "title": "Textron Wins Order to Supply up to 12 Citation Jets in Mexico",
    "link": "https://finance.yahoo.com/news/textron-wins-order-supply-12-145300843.html"
  },
  {
    "title": "Trump’s DOJ agrees to let Boeing escape guilty plea. It was a deal victims’ families didn’t want.",
    "link": "https://finance.yahoo.com/news/trumps-doj-agrees-to-let-boeing-escape-guilty-plea-it-was-a-deal-victims-families-didnt-want-080005748.html"
  },
  {
    "title": "Trump Said Qatar Gifted Him A $400 Million Jet, But Insiders Say The US Initiated The Deal",
    "link": "https://finance.yahoo.com/news/trump-said-qatar-gifted-him-013134807.html"
  },
  {
    "title": "737 Max Families Demand Criminal Trial for Boeing",
    "link": "https://finance.yahoo.com/news/737-max-families-demand-criminal-210857337.html"
  },
  {
    "title": "US should take Boeing to trial in 737 MAX fraud case, lawyer says",
    "link": "https://finance.yahoo.com/news/us-boeing-trial-737-max-143147113.html"
  },
  {
    "title": "Boeing back in 'dynamic' production mode, engine supplier Safran says",
    "link": "https://finance.yahoo.com/news/boeing-back-dynamic-production-mode-141716979.html"
  },
  {
    "title": "RTX's Unit Secures a Contract to Aid AIM-9X Sidewinder Missile Systems",
    "link": "https://finance.yahoo.com/news/rtxs-unit-secures-contract-aid-134900514.html"
  },
  {
    "title": "Lessor SMBC says Boeing and Airbus output has made some progress",
    "link": "https://finance.yahoo.com/news/lessor-smbc-says-boeing-airbus-060630718.html"
  },
  {
    "title": "Boeing Speeds Up 737 Manufacturing as Safety and Quality Standards Rise",
    "link": "https://finance.yahoo.com/news/boeing-speeds-737-manufacturing-safety-031628612.html"
  },
  {
    "title": "Pentagon Says It Has Taken Possession of 747 From Qatar",
    "link": "https://finance.yahoo.com/m/ddea97fe-a484-30aa-8386-391ef792512d/pentagon-says-it-has-taken.html"
  },
  {
    "title": "Bernstein Maintains Outperform Rating on Boeing (BA), Lifts PT",
    "link": "https://finance.yahoo.com/news/bernstein-maintains-outperform-rating-boeing-173715142.html"
  },
  {
    "title": "Market Chatter: Boeing Looks to Stabilize 737 Production at 38 Units per Month",
    "link": "https://finance.yahoo.com/news/market-chatter-boeing-looks-stabilize-152547342.html"
  },
  {
    "title": "RTX's Arm Wins a $1B Contract to Aid Standard Missile-3 Program",
    "link": "https://finance.yahoo.com/news/rtxs-arm-wins-1b-contract-151700291.html"
  },
  {
    "title": "Boeing increases 737 production pace as quality, safety culture improves",
    "link": "https://finance.yahoo.com/news/boeing-increases-737-production-pace-140221731.html"
  },
  {
    "title": "Boeing’s Internal Safety Plan: Make Problems Easier to Report",
    "link": "https://finance.yahoo.com/m/7870f527-7eeb-3bcf-97b0-d402a084eb07/boeing%E2%80%99s-internal-safety.html"
  },
  {
    "title": "Trump's Former VP Mike Pence Calls Qatari Royal Family's Boeing Jet Gift A 'Bad Idea,' Urges President To Reject $400 Million 'Flying Palace'",
    "link": "https://finance.yahoo.com/news/trumps-former-vp-mike-pence-213011732.html"
  },
  {
    "title": "Boeing Stock Price Targets Are Rising. Where Shares Can Go Now.",
    "link": "https://finance.yahoo.com/m/8387d408-bed2-312c-8699-0150be82e95c/boeing-stock-price-targets.html"
  },
  {
    "title": "DAL vs. LUV: Which Airline Stock is a Stronger Play Now?",
    "link": "https://finance.yahoo.com/news/dal-vs-luv-airline-stock-142000272.html"
  },
  {
    "title": "Qatar denies Trump’s $400m luxury plane is a bribe",
    "link": "https://finance.yahoo.com/news/qatar-denies-trump-400m-luxury-114320918.html"
  },
  {
    "title": "Ryanair fares set to rise by nearly 20% as airline plots profit rebound",
    "link": "https://finance.yahoo.com/news/ryanair-fares-set-rise-nearly-073627273.html"
  },
  {
    "title": "Boeing Stock Is Down. The 737 MAX Charges May Be Decided This Week.",
    "link": "https://finance.yahoo.com/m/dcf59b34-f01c-365d-a17d-a1326606686e/boeing-stock-is-down-the-737.html"
  },
  {
    "title": "DCO Q1 Earnings Call: Defense Growth Offsets Commercial Aerospace Weakness, Margin Expansion Continues",
    "link": "https://finance.yahoo.com/news/dco-q1-earnings-call-defense-122335297.html"
  },
  {
    "title": "Market Chatter: Boeing Faces Opposition from Crash Victims' Families Over DOJ Deal",
    "link": "https://finance.yahoo.com/news/market-chatter-boeing-faces-opposition-103503675.html"
  },
  {
    "title": "Ryanair to raise prices as it seeks return to profit growth",
    "link": "https://finance.yahoo.com/news/ryanair-raise-prices-seeks-return-082210805.html"
  },
  {
    "title": "Ryanair CEO on Earnings, Tariffs, Buybacks, Boeing",
    "link": "https://finance.yahoo.com/video/ryanair-ceo-earnings-tariffs-buybacks-064424559.html"
  },
  {
    "title": "1 Large-Cap Stock to Keep an Eye On and 2 to Question",
    "link": "https://finance.yahoo.com/news/1-large-cap-stock-keep-044126257.html"
  },
  {
    "title": "Boeing, GE and Trump’s Middle East trip to remember",
    "link": "https://finance.yahoo.com/news/boeing-ge-trump-middle-east-130038851.html"
  },
  {
    "title": "Jim Cramer On Boeing Company (BA): “The Loser Became a Winner”",
    "link": "https://finance.yahoo.com/news/jim-cramer-boeing-company-ba-105815531.html"
  },
  {
    "title": "Families of 737 MAX crash victims to object to deal allowing Boeing to avoid prosecution",
    "link": "https://finance.yahoo.com/news/families-737-max-crash-victims-195809652.html"
  },
  {
    "title": "Charter to combine with Cox, Take-Two reports mixed Q4 results: Morning Buzz",
    "link": "https://finance.yahoo.com/news/charter-combine-cox-two-reports-160646050.html"
  },
  {
    "title": "President Trump Just Cut the Budget on Boeing's and Lockheed's Most Important Space Program",
    "link": "https://finance.yahoo.com/news/president-trump-just-cut-budget-110700328.html"
  },
  {
    "title": "’From Tariff Man to Global Salesman’",
    "link": "https://finance.yahoo.com/news/tariff-man-global-salesman-094214337.html"
  },
  {
    "title": "Peter Schiff Warns Qatar's $200 Billion Boeing Deal Could Spike US Inflation, Interest Rates — Says Treasury Sell-Off May Follow",
    "link": "https://finance.yahoo.com/news/peter-schiff-warns-qatars-200-023143964.html"
  },
  {
    "title": "U.S. Won’t Prosecute Boeing Over 737 MAX Crashes, WSJ Reports",
    "link": "https://finance.yahoo.com/m/f303400e-ad5b-35c7-a352-1e8c526959df/u-s-won%E2%80%99t-prosecute-boeing.html"
  },
  {
    "title": "Justice Department Wants to Spare Boeing From Guilty Plea Over 737 MAX Charges",
    "link": "https://finance.yahoo.com/m/19f8d86d-8062-3dab-9990-c4ec21ab51c4/justice-department-wants-to.html"
  },
  {
    "title": "Boeing Won't Be Prosecuted by DOJ Over Violating Criminal Settlement, Report Says",
    "link": "https://finance.yahoo.com/news/boeing-wont-prosecuted-doj-over-201000350.html"
  },
  {
    "title": "Trump Strikes $14.5B Jet Deal in UAE--Boeing and GE Soar Back Into the Spotlight",
    "link": "https://finance.yahoo.com/news/trump-strikes-14-5b-jet-172540993.html"
  },
  {
    "title": "Top Midday Stories: Novo Nordisk CEO Stepping Down; Charter, Cox to Merge in $34.5 Billion Deal",
    "link": "https://finance.yahoo.com/news/top-midday-stories-novo-nordisk-153350245.html"
  },
  {
    "title": "Exclusive-Boeing nears deal to avoid guilty plea, prosecution in 737 MAX crashes case, sources say",
    "link": "https://finance.yahoo.com/news/exclusive-boeing-near-deal-avoid-144421545.html"
  },
  {
    "title": "Boeing Secures a Contract for 210 Widebody Aircraft From Qatar Airways",
    "link": "https://finance.yahoo.com/news/boeing-secures-contract-210-widebody-141100850.html"
  },
  {
    "title": "Beyond the headlines: explaining Trump's Gulf 'trillions'",
    "link": "https://finance.yahoo.com/news/beyond-headlines-explaining-trumps-gulf-133547882.html"
  },
  {
    "title": "Boeing Lands $14.5B Jet Deal With Etihad as Trump Visits UAE",
    "link": "https://finance.yahoo.com/news/boeing-lands-14-5b-jet-131331717.html"
  },
  {
    "title": "Boeing, GE Aerospace, ExxonMobil Reportedly Benificiaries of UAE Deals",
    "link": "https://finance.yahoo.com/news/boeing-ge-aerospace-exxonmobil-reportedly-102932372.html"
  },
  {
    "title": "Gold Palaces, Jet Deals and McDonald’s: Trump at Home in Middle East",
    "link": "https://finance.yahoo.com/news/gold-palaces-jet-deals-mcdonald-100717163.html"
  },
  {
    "title": "Why so many CEOs crossed paths with Trump in the Middle East, from Sam Altman to Jensen Huang",
    "link": "https://finance.yahoo.com/news/why-so-many-ceos-crossed-paths-with-trump-in-the-middle-east-from-sam-altman-to-jensen-huang-080000141.html"
  },
  {
    "title": "As Nikki Haley Slams Trump's $400 Million Boeing Jet Gift From Qatar, Bill Ackman Cites National Security Implications: 'Only A Fool Would Not Accept This,' Says President",
    "link": "https://finance.yahoo.com/news/nikki-haley-slams-trumps-400-023009868.html"
  },
  {
    "title": "Boeing Stock Rises Again. Wall Street Is More Positive on Sales.",
    "link": "https://finance.yahoo.com/m/9d480328-cd2b-30b2-abfb-18b29068511a/boeing-stock-rises-again-.html"
  },
  {
    "title": "Jim Cramer Urges Investors to “Stay Long Boeing”",
    "link": "https://finance.yahoo.com/news/jim-cramer-urges-investors-stay-192526470.html"
  },
  {
    "title": "Boeing Could Be 'The Big Winner' in Long-Term China Trade Deal, Analyst Says",
    "link": "https://finance.yahoo.com/news/boeing-could-big-winner-long-174950218.html"
  },
  {
    "title": "UnitedHealth stock, Boot Barn on top of tariffs, Boeing boosted",
    "link": "https://finance.yahoo.com/video/unitedhealth-stock-boot-barn-top-160912354.html"
  },
  {
    "title": "White House touts Boeing aircraft, GE Aerospace engine sales to Qatar",
    "link": "https://finance.yahoo.com/news/white-house-touts-boeing-aircraft-154020644.html"
  },
  {
    "title": "Boeing (BA) Secures $96B Jet Deal as Trump Makes Aviation Diplomacy Personal",
    "link": "https://finance.yahoo.com/news/boeing-ba-secures-96b-jet-131804186.html"
  },
  {
    "title": "Lockheed Loses 16% in 6 Months: Should You Buy the Stock Now?",
    "link": "https://finance.yahoo.com/news/lockheed-loses-16-6-months-123700027.html"
  },
  {
    "title": "Boeing Wins Order to Provide AviLease With up to 30 737-8 Aircraft",
    "link": "https://finance.yahoo.com/news/boeing-wins-order-avilease-30-123700455.html"
  },
  {
    "title": "Boeing stock target raised at Wolfe after ’a big beautiful order’ from Qatar",
    "link": "https://finance.yahoo.com/news/boeing-stock-target-raised-wolfe-121625629.html"
  },
  {
    "title": "Boeing Booms From Trump’s Trade Deals. This Can Lift Aerospace, Defense Stocks Higher.",
    "link": "https://finance.yahoo.com/m/ecbdd497-72d2-3d60-8b24-f55693f5d3e6/boeing-booms-from-trump%E2%80%99s.html"
  },
  {
    "title": "Boeing, GE Aerospace Secure $96 Billion Qatar Airways Order for Widebody Jets, Engines",
    "link": "https://finance.yahoo.com/news/boeing-ge-aerospace-secure-96-103523462.html"
  },
  {
    "title": "Trending tickers: Boeing, Cisco, Foot Locker, ITV and Aviva",
    "link": "https://finance.yahoo.com/news/boeing-cisco-foot-locker-itv-aviva-trending-tickers-101825869.html"
  },
  {
    "title": "New Boeing distribution centre strengthens Europe support",
    "link": "https://finance.yahoo.com/news/boeing-distribution-centre-strengthens-europe-093130937.html"
  },
  {
    "title": "Boeing Soaring on Trump Bump: Time to Tap the ETFs?",
    "link": "https://finance.yahoo.com/news/boeing-soaring-trump-bump-time-080000871.html"
  },
  {
    "title": "Boeing secures ‘largest-ever’ order from Qatar during Trump visit",
    "link": "https://finance.yahoo.com/news/boeing-secures-largest-ever-order-045619696.html"
  },
  {
    "title": "AP Top Financial News at 11:44 p.m. EDT",
    "link": "https://finance.yahoo.com/news/ap-top-financial-news-3-040000786.html"
  },
  {
    "title": "AP Top Extended Financial Headlines at 11:44 p.m. EDT",
    "link": "https://finance.yahoo.com/news/ap-top-extended-financial-headlines-040000214.html"
  },
  {
    "title": "US Justice Department to meet families of 737 MAX victims on Boeing criminal case",
    "link": "https://finance.yahoo.com/news/us-justice-department-meet-737-022112631.html"
  },
  {
    "title": "Trump Just Locked In $243.5 Billion from Qatar -- And That's Just the Opening Act",
    "link": "https://finance.yahoo.com/news/trump-just-locked-243-5-223054687.html"
  },
  {
    "title": "Boeing Stock Is Rising. Qatar Is Helping.",
    "link": "https://finance.yahoo.com/m/6975d951-fecc-3000-90e8-3bad1a2ccbed/boeing-stock-is-rising-qatar.html"
  },
  {
    "title": "Boeing and Qatar Airways Announce Historic Order for up to 210 Widebody Airplanes",
    "link": "https://finance.yahoo.com/news/boeing-qatar-airways-announce-historic-191000860.html"
  },
  {
    "title": "Boeing, trying to emerge from one of company's most difficult eras, is having a pretty good week",
    "link": "https://finance.yahoo.com/news/boeing-trying-emerge-one-companys-183127832.html"
  },
  {
    "title": "Boeing gets its biggest 787 jet order ever from Qatar Airways, the White House says",
    "link": "https://finance.yahoo.com/news/boeing-gets-biggest-787-jet-172400445.html"
  },
  {
    "title": "Jim Cramer Says You Should Buy Boeing (BA) Amid ‘Multi-Year Runway’",
    "link": "https://finance.yahoo.com/news/jim-cramer-says-buy-boeing-164218616.html"
  },
  {
    "title": "Boeing stock takes off thanks to President Trump as the plane maker scores its biggest order ever",
    "link": "https://finance.yahoo.com/news/boeing-stock-takes-off-thanks-to-president-trump-as-the-plane-maker-scores-its-biggest-order-ever-164142935.html"
  },
  {
    "title": "US Announces More Than $243 Billion in Deals With Qatar",
    "link": "https://finance.yahoo.com/news/us-announces-more-243-billion-161612131.html"
  },
  {
    "title": "WH announces $1.2T in economic commitment with Qatar, including significant Boeing order",
    "link": "https://finance.yahoo.com/news/wh-announces-1-2t-economic-161516393.html"
  },
  {
    "title": "Trump’s Freebie Qatar Jet Is Nightmare Scenario in Spyworld",
    "link": "https://finance.yahoo.com/news/trump-freebie-qatar-jet-stuff-213849085.html"
  },
  {
    "title": "Top Midday Stories: Qatar Orders 160 Boeing Jets for Over $200 Billion; Super Micro, DataVolt Form $20 Billion Partnership",
    "link": "https://finance.yahoo.com/news/top-midday-stories-qatar-orders-153427521.html"
  },
  {
    "title": "Trump Touts Record Boeing Order From Qatar Airways",
    "link": "https://finance.yahoo.com/video/trump-touts-record-boeing-order-150810257.html"
  },
  {
    "title": "Boeing stock gains after record jet order from Qatar",
    "link": "https://finance.yahoo.com/news/boeing-stock-gains-record-jet-150037363.html"
  },
  {
    "title": "Qatar Airways to make largest ever Boeing order, Trump says",
    "link": "https://finance.yahoo.com/video/qatar-airways-largest-ever-boeing-145306390.html"
  },
  {
    "title": "Trump Says Qatar's Jet Order Is Largest in Boeing's History",
    "link": "https://finance.yahoo.com/video/trump-says-qatars-jet-order-143503359.html"
  },
  {
    "title": "RTX's Arm Wins a $2.13B Contract to Aid Standard Missile-3 Program",
    "link": "https://finance.yahoo.com/news/rtxs-arm-wins-2-13b-143200521.html"
  },
  {
    "title": "White House calls out Boeing, GE Vernova exports in Saudi Arabia pact",
    "link": "https://finance.yahoo.com/news/white-house-calls-boeing-ge-142742667.html"
  },
  {
    "title": "Qatar Airways orders 160 Boeing twin-aisle jets during Trump visit",
    "link": "https://finance.yahoo.com/news/qatar-signs-200-billion-deal-141829225.html"
  },
  {
    "title": "Barclays and J&J Snack Foods have been highlighted as Zacks Bull and Bear of the Day",
    "link": "https://finance.yahoo.com/news/barclays-j-j-snack-foods-132700192.html"
  },
  {
    "title": "Here is What to Know Beyond Why The Boeing Company (BA) is a Trending Stock",
    "link": "https://finance.yahoo.com/news/know-beyond-why-boeing-company-130015435.html"
  },
  {
    "title": "You can't manage risk if you don't know what you're holding",
    "link": "https://finance.yahoo.com/video/cant-manage-risk-dont-know-110014557.html"
  },
  {
    "title": "China Just Reopened Its Skies to Boeing",
    "link": "https://finance.yahoo.com/news/china-just-reopened-skies-boeing-083142416.html"
  },
  {
    "title": "In Trump’s World, Jets Are Key to Unlocking Political Favors",
    "link": "https://finance.yahoo.com/news/trump-world-aircraft-key-unlocking-020000581.html"
  },
  {
    "title": "Boeing (BA) Gains as China Lifts Aircraft Ban Following 90-Day Trade Truce",
    "link": "https://finance.yahoo.com/news/boeing-ba-gains-china-lifts-204327986.html"
  },
  {
    "title": "Tesla Investor Ron Baron Calls Defense Industry ‘Corrupt,’ Has Tough Words for Boeing",
    "link": "https://finance.yahoo.com/m/50be8536-6218-3879-b96b-22c411b3f3a4/tesla-investor-ron-baron.html"
  },
  {
    "title": "Boeing Stock Rose. Why It’s Getting a Boost From Tariff Talks Breakthrough.",
    "link": "https://finance.yahoo.com/m/84569ee6-4b44-3878-8bc4-463b8abf1335/boeing-stock-rose-why-it%E2%80%99s.html"
  },
  {
    "title": "Stocks to Watch Tuesday: Coinbase, Boeing, Hertz, UnitedHealth",
    "link": "https://finance.yahoo.com/m/eb087028-0d77-362b-8172-9d6e24966ff9/stocks-to-watch-tuesday-.html"
  },
  {
    "title": "These Stocks Moved the Most Today: UnitedHealth, Nvidia, Tesla, First Solar, Coinbase, Palantir, Super Micro, Boeing, Rigetti, and More",
    "link": "https://finance.yahoo.com/m/fc86b53d-82e1-384c-9c1d-e83270eff7e2/these-stocks-moved-the-most.html"
  },
  {
    "title": "Boeing's Commercial Aircraft Deliveries Rise in April",
    "link": "https://finance.yahoo.com/news/boeing-apos-commercial-aircraft-deliveries-193530192.html"
  },
  {
    "title": "Boeing Hits 52-Week High After China Reverses Delivery Ban",
    "link": "https://finance.yahoo.com/m/87957744-8ece-30ca-9d59-0ed8b4db057f/boeing-hits-52-week-high.html"
  },
  {
    "title": "Trump and MBS Tout $1 Trillion Pledge as Details Remain Elusive",
    "link": "https://finance.yahoo.com/news/trump-mbs-tout-1-trillion-174902305.html"
  },
  {
    "title": "RTX's PhantomStrike Radar Catches Spotlight: Should You Buy the Stock Now?",
    "link": "https://finance.yahoo.com/news/rtxs-phantomstrike-radar-catches-spotlight-173100716.html"
  },
  {
    "title": "United Airlines exec says it may not get Boeing 737 MAX 10s until 2027 or '28",
    "link": "https://finance.yahoo.com/news/united-airlines-exec-says-may-173052141.html"
  },
  {
    "title": "Boeing Wins Order for 777X Aircraft: Should You Buy or Sell the Stock Now?",
    "link": "https://finance.yahoo.com/news/boeing-wins-order-777x-aircraft-172800648.html"
  },
  {
    "title": "China Lifts Restrictions on Boeing Plane Deliveries",
    "link": "https://finance.yahoo.com/m/9fdb6388-3706-356d-8342-bd993d8a25be/china-lifts-restrictions-on.html"
  },
  {
    "title": "The Zacks Analyst Blog Highlights Texas Instruments, Boeing, NextEra",
    "link": "https://finance.yahoo.com/news/zacks-analyst-blog-highlights-texas-152900047.html"
  },
  {
    "title": "Boeing deliveries nearly double in April",
    "link": "https://finance.yahoo.com/news/boeing-deliveries-nearly-double-april-150804003.html"
  },
  {
    "title": "AviLease Places First Direct Boeing Order for up to 30 737 MAX Jets",
    "link": "https://finance.yahoo.com/news/avilease-places-first-direct-boeing-143500312.html"
  },
  {
    "title": "Trump Diplomatic Blitz Spins Big Gambles as Signs of Success",
    "link": "https://finance.yahoo.com/news/trump-diplomatic-blitz-spins-big-142233091.html"
  },
  {
    "title": "Saudi Arabia's AviLease places order for up to 30 Boeing 737 MAX jets",
    "link": "https://finance.yahoo.com/news/saudi-arabia-wealth-fund-order-141954558.html"
  },
  {
    "title": "Boeing gets a break in China",
    "link": "https://finance.yahoo.com/news/boeing-gets-break-china-135700630.html"
  },
  {
    "title": "China unbans Boeing, United CEO on safety, Coinbase to join S&P 500",
    "link": "https://finance.yahoo.com/video/china-unbans-boeing-united-ceo-134631476.html"
  },
  {
    "title": "NYSE Content Advisory: Pre-Market update + April Consumer Inflation Data released",
    "link": "https://finance.yahoo.com/news/nyse-content-advisory-pre-market-125500599.html"
  },
  {
    "title": "5 Things to Know Before the Stock Market Opens",
    "link": "https://finance.yahoo.com/news/5-things-know-stock-market-115547833.html"
  },
  {
    "title": "China removes ban on Boeing deliveries after deal with US to temporarily slash tariffs",
    "link": "https://finance.yahoo.com/news/china-removes-ban-boeing-deliveries-100411525.html"
  },
  {
    "title": "China reportedly removes Boeing bar",
    "link": "https://finance.yahoo.com/news/china-reportedly-removes-boeing-bar-094608363.html"
  },
  {
    "title": "Trending tickers: Coinbase, Amazon, Meta, Boeing and M&S",
    "link": "https://finance.yahoo.com/news/coinbase-amazon-meta-boeing-marks-spencer-trending-tickers-084308639.html"
  },
  {
    "title": "FTSE closes flat, Wall Street mixed as US consumer inflation data comes in cool",
    "link": "https://finance.yahoo.com/news/live/ftse-100-live-stocks-uk-jobs-market-weakens-081252160.html"
  },
  {
    "title": "Boeing's China Deliveries to Resume After Ban Lifted",
    "link": "https://finance.yahoo.com/video/boeings-china-deliveries-resume-ban-061224789.html"
  },
  {
    "title": "China lifts Boeing delivery ban as tariff war cools, Bloomberg News reports",
    "link": "https://finance.yahoo.com/news/china-removes-ban-boeing-deliveries-052348190.html"
  },
  {
    "title": "Boeing Has an Air Force One Deal. How Qatar’s Gift Fits In.",
    "link": "https://finance.yahoo.com/m/f0c90958-9118-39c8-95cf-d0f3f44794d7/boeing-has-an-air-force-one.html"
  },
  {
    "title": "Top Research Reports for Texas Instruments, Boeing & NextEra Energy",
    "link": "https://finance.yahoo.com/news/top-research-reports-texas-instruments-201800269.html"
  },
  {
    "title": "How Should an Investor Play LUNR Stock Pre-Q1 Earnings Release?",
    "link": "https://finance.yahoo.com/news/investor-play-lunr-stock-pre-124900517.html"
  },
  {
    "title": "Trump Set to Accept Luxury Jet as Gift From Qatar, ABC Says",
    "link": "https://finance.yahoo.com/news/trump-set-accept-luxury-jet-015931693.html"
  },
  {
    "title": "U.S.-China Talks End: Bessent Touts 'Substantial Progress'; White House Signals Deal",
    "link": "https://finance.yahoo.com/m/a6293ac4-2f26-3ac3-a8ce-f7175309469a/u-s-china-talks-end-bessent.html"
  },
  {
    "title": "Stephen Miller Says 'History Will Record' Trump's Tariffs As The Start Of Saving The West From China's Economic Domination'",
    "link": "https://finance.yahoo.com/news/stephen-miller-says-history-record-190024839.html"
  },
  {
    "title": "Flash! Boeing is on a roll",
    "link": "https://finance.yahoo.com/news/flash-boeing-roll-081014261.html"
  },
  {
    "title": "The Score: Disney, Berkshire Hathaway, Ford and More Stocks That Defined the Week",
    "link": "https://finance.yahoo.com/m/832574ac-99ac-34a8-8772-b496a6204724/the-score-disney-berkshire.html"
  },
  {
    "title": "Boeing Stock Rises. Trump Was Right.",
    "link": "https://finance.yahoo.com/m/cdffbb69-19ef-3c3b-b27b-d45057e97b2e/boeing-stock-rises-trump-was.html"
  },
  {
    "title": "Boeing is the big winner in Trump's first trade deal",
    "link": "https://finance.yahoo.com/news/boeing-big-winner-trumps-first-184529301.html"
  },
  {
    "title": "How British Airways helped land Starmer’s trade deal with Trump",
    "link": "https://finance.yahoo.com/news/british-airways-helped-land-starmer-124953327.html"
  },
  {
    "title": "Stock Market Today: Dow Jones Rises On Trump Tariff Comments; Cloudflare, Lyft Surge On Earnings",
    "link": "https://finance.yahoo.com/m/8a91b68f-721c-34cf-aa78-09d8ce36d55c/stock-market-today-dow-jones.html"
  },
  {
    "title": "EU Tells Trump: No Side Deals or Shortcuts on Trade Negotiations",
    "link": "https://finance.yahoo.com/news/eu-tells-trump-no-side-115009467.html"
  },
  {
    "title": "Boeing is the first winner in new era of piecemeal trade deals",
    "link": "https://finance.yahoo.com/news/boeing-is-the-first-winner-in-new-era-of-piecemeal-trade-deals-100052185.html"
  },
  {
    "title": "Trending tickers: TSMC, Lyft, Coinbase, Pinterest and IAG",
    "link": "https://finance.yahoo.com/news/tsmc-lyft-coinbase-pinterest-iag-trending-tickers-090412594.html"
  },
  {
    "title": "British Airways Owner IAG to Buy 53 Boeing and Airbus Planes Despite Market Uncertainty",
    "link": "https://finance.yahoo.com/m/36b8da92-5f37-30ef-9b3d-a1ca0fd09119/british-airways-owner-iag-to.html"
  },
  {
    "title": "British Airways owner IAG buys 32 new Boeing planes from US amid trade deal",
    "link": "https://finance.yahoo.com/news/british-airways-owner-iag-buys-063901232.html"
  },
  {
    "title": "IAG orders 71 long-haul jets split between Airbus and Boeing",
    "link": "https://finance.yahoo.com/news/british-airways-owner-iag-orders-061114214.html"
  },
  {
    "title": "Stocks to Watch Recap: Coinbase, Boeing, Intel, Krispy Kreme",
    "link": "https://finance.yahoo.com/m/b78b55ec-77d9-384a-8c79-2d47ed158ce2/stocks-to-watch-recap-.html"
  },
  {
    "title": "Stock Market Today: Dow Jones Finishes 250 Points Higher On U.S.-UK Trade Deal; Boeing Soars Past Buy Point, Bitcoin Races Past $100,000 (Live Coverage)",
    "link": "https://finance.yahoo.com/m/2e38cec8-2dfe-3e4e-8f7e-13dab3783f67/stock-market-today-dow-jones.html"
  },
  {
    "title": "Boeing Stock Jumps on Trade News. It Isn’t About Plane Sales to the U.K.",
    "link": "https://finance.yahoo.com/m/b0fa6a09-e7de-311c-9d04-2d9b949db2fc/boeing-stock-jumps-on-trade.html"
  },
  {
    "title": "$10 Billion Mystery Deal Sends Boeing Soaring -- But Who's Cutting the Check?",
    "link": "https://finance.yahoo.com/news/10-billion-mystery-deal-sends-185000017.html"
  },
  {
    "title": "British Airways parent IAG to order about 30 jets from Boeing, Bloomberg News reports",
    "link": "https://finance.yahoo.com/news/british-airways-parent-iag-order-175058502.html"
  },
  {
    "title": "UK-US trade deal benefits Rolls-Royce amid tepid FTSE",
    "link": "https://finance.yahoo.com/news/uk-us-trade-deal-rolls-royce-donald-trump-keir-starmer-174744477.html"
  },
  {
    "title": "Boeing, Defense Stocks Take Off, But No Thanks To Industry Giants Lockheed, Northrop",
    "link": "https://finance.yahoo.com/m/cb82d00a-a43f-32ad-a385-b57e536cc254/boeing-defense-stocks-take.html"
  },
  {
    "title": "Trump admin. announces $10B Boeing deal with an UK airline",
    "link": "https://finance.yahoo.com/video/trump-admin-announces-10b-boeing-173000895.html"
  },
  {
    "title": "Trump confirms trade deal with U.K.",
    "link": "https://finance.yahoo.com/news/trump-confirms-first-trade-deal-160524366.html"
  },
  {
    "title": "Britain's IAG to buy Boeing and Airbus jets, sources say",
    "link": "https://finance.yahoo.com/news/uk-announce-10-billion-boeing-152550586.html"
  },
  {
    "title": "Lutnick Says a U.K. Airline Will Buy $10 Billion Worth of Boeing Jets",
    "link": "https://finance.yahoo.com/m/fee31b53-afe4-385b-9958-261c09cb35ad/lutnick-says-a-u-k-airline.html"
  },
  {
    "title": "Boeing Secures Order From Taiwan's China Airlines",
    "link": "https://finance.yahoo.com/news/boeing-secures-order-taiwans-china-145142286.html"
  },
  {
    "title": "China Airlines finalizes deal for 4 Boeing 777-8 cargo aircraft",
    "link": "https://finance.yahoo.com/news/china-airlines-finalizes-deal-4-132041055.html"
  },
  {
    "title": "Trump announces his first trade deal with the UK. Here's what's in it.",
    "link": "https://finance.yahoo.com/news/trump-announces-his-first-trade-deal-with-the-uk-heres-whats-in-it-120417143.html"
  },
  {
    "title": "EU to Target US Cars, Planes, Bourbon If Trump Won’t Do a Deal",
    "link": "https://finance.yahoo.com/news/eu-target-us-cars-planes-120000251.html"
  },
  {
    "title": "Taiwan's China Airlines orders 14 Boeing 777X planes",
    "link": "https://finance.yahoo.com/news/taiwans-china-airlines-orders-14-075822458.html"
  },
  {
    "title": "China Airlines Announces Order for Boeing 777X Passenger and Freighter Models",
    "link": "https://finance.yahoo.com/news/china-airlines-announces-order-boeing-073000285.html"
  },
  {
    "title": "Boeing proposes 2027 delivery date for new Air Force One jets, official says",
    "link": "https://finance.yahoo.com/news/boeing-proposes-2027-delivery-date-003227234.html"
  },
  {
    "title": "Boeing taps Wisk Aero CEO to head commercial airplane product development",
    "link": "https://finance.yahoo.com/news/boeing-taps-wisk-aero-ceo-200628612.html"
  },
  {
    "title": "Is The Boeing Company (BA) the Best Dow Stock?",
    "link": "https://finance.yahoo.com/news/boeing-company-ba-best-dow-181039953.html"
  },
  {
    "title": "EU to Hit Boeing, US Cars With Tariffs If Trade Talks Fail",
    "link": "https://finance.yahoo.com/news/eu-plans-hit-boeing-tariffs-104422699.html"
  },
  {
    "title": "Aerospace faces wider tariffs as Europe draws up retaliation",
    "link": "https://finance.yahoo.com/news/eu-considers-tariffs-boeing-jets-100047620.html"
  },
  {
    "title": "Qatar Airways Lining Up Major Boeing Order",
    "link": "https://finance.yahoo.com/video/qatar-airways-lining-major-boeing-081455719.html"
  },
  {
    "title": "Astronics Corp (ATRO) Q1 2025 Earnings Call Highlights: Record Aerospace Performance and Strong ...",
    "link": "https://finance.yahoo.com/news/astronics-corp-atro-q1-2025-072149370.html"
  },
  {
    "title": "Ducommun Inc (DCO) Q1 2025 Earnings Call Highlights: Record Margins and Defense Growth Amidst ...",
    "link": "https://finance.yahoo.com/news/ducommun-inc-dco-q1-2025-071840817.html"
  },
  {
    "title": "EU Eyes €100 Billion of US Goods With Tariffs If Talks Fail",
    "link": "https://finance.yahoo.com/news/eu-targets-100-billion-us-112326701.html"
  },
  {
    "title": "Qatar Airways set to order about 100 widebody jets from Boeing, Bloomberg News reports",
    "link": "https://finance.yahoo.com/news/qatar-airways-set-order-100-121857138.html"
  },
  {
    "title": "AerSale (ASLE) Q1 Earnings: What To Expect",
    "link": "https://finance.yahoo.com/news/aersale-asle-q1-earnings-expect-070947644.html"
  },
  {
    "title": "Curtiss-Wright (CW) Reports Q1: Everything You Need To Know Ahead Of Earnings",
    "link": "https://finance.yahoo.com/news/curtiss-wright-cw-reports-q1-070914450.html"
  },
  {
    "title": "India Offers Zero-for-Zero Tariffs on Auto Parts, Steel From US",
    "link": "https://finance.yahoo.com/news/india-offers-zero-zero-tariffs-142116336.html"
  },
  {
    "title": "How to Boost Your Portfolio with Top Aerospace Stocks Set to Beat Earnings",
    "link": "https://finance.yahoo.com/news/boost-portfolio-top-aerospace-stocks-130006137.html"
  },
  {
    "title": "Spirit AeroSystems plans furloughs at Kansas facility",
    "link": "https://finance.yahoo.com/news/spirit-aerosystems-plans-furloughs-kansas-122558057.html"
  },
  {
    "title": "Trump’s NASA Nominee Backs Funding Method That Benefitted SpaceX",
    "link": "https://finance.yahoo.com/news/trump-nasa-nominee-backs-funding-090027080.html"
  },
  {
    "title": "Astronics Earnings: What To Look For From ATRO",
    "link": "https://finance.yahoo.com/news/astronics-earnings-look-atro-071359218.html"
  },
  {
    "title": "Ducommun Earnings: What To Look For From DCO",
    "link": "https://finance.yahoo.com/news/ducommun-earnings-look-dco-070921155.html"
  },
  {
    "title": "TransDigm (TDG) Q1 Earnings: What To Expect",
    "link": "https://finance.yahoo.com/news/transdigm-tdg-q1-earnings-expect-070330362.html"
  }
]